discogui/__init__.py
discogui/about.py
discogui/buttons.py
discogui/draw.py
discogui/hover.py
discogui/imglog.py
discogui/imgutil.py
discogui/mouse.py
discogui/screenrect.py
discogui/taborder.py
discogui/examples/__init__.py
discogui/examples/blink.py
discogui/examples/clickbutton.py
discogui/examples/hover.py
discogui/examples/taborder.py
discogui-0.5.dist-info/LICENSE.txt
discogui-0.5.dist-info/METADATA
discogui-0.5.dist-info/WHEEL
discogui-0.5.dist-info/top_level.txt
discogui-0.5.dist-info/RECORD
