Metadata-Version: 2.1
Name: discogui
Version: 0.5
Summary: GUI discovery
Home-page: https://github.com/ponty/discogui
Author: ponty
License: BSD
Keywords: GUI
Platform: UNKNOWN
Classifier: License :: OSI Approved :: BSD License
Classifier: Natural Language :: English
Classifier: Operating System :: OS Independent
Classifier: Programming Language :: Python
Classifier: Programming Language :: Python :: 3
Classifier: Programming Language :: Python :: 3 :: Only
Classifier: Programming Language :: Python :: 3.10
Classifier: Programming Language :: Python :: 3.11
Classifier: Programming Language :: Python :: 3.12
License-File: LICENSE.txt
Requires-Dist: PyScreenshot
Requires-Dist: PyUserInput
Requires-Dist: easyprocess
Requires-Dist: pillow
Requires-Dist: pyvirtualdisplay
